stock_viewer/__init__.py
stock_viewer/about.py
stock_viewer/desktop.py
stock_viewer/prog_viewer.py
stock_viewer/icons/logo.png
stock_viewer/modules/__init__.py
stock_viewer/modules/categorize.py
stock_viewer/modules/configure.py
stock_viewer/modules/stock.py
stock_viewer/modules/stock_old.py
stock_viewer/modules/stockb3.py
stock_viewer/modules/text_editor.py
stock_viewer/modules/wabout.py
stock_viewer-0.1.14.dist-info/licenses/LICENSE
stock_viewer-0.1.14.dist-info/METADATA
stock_viewer-0.1.14.dist-info/WHEEL
stock_viewer-0.1.14.dist-info/entry_points.txt
stock_viewer-0.1.14.dist-info/top_level.txt
stock_viewer-0.1.14.dist-info/RECORD
