Metadata-Version: 2.4
Name: stock_viewer
Version: 0.1.14
Summary: Simple stock viewer program.
Author-email: Fernando Pujaico Rivera <fernando.pujaico.rivera@gmail.com>
Maintainer-email: Fernando Pujaico Rivera <fernando.pujaico.rivera@gmail.com>
License-Expression: GPL-3.0-only WITH Classpath-exception-2.0 OR BSD-3-Clause
Project-URL: Bug Reports, https://github.com/trucomanx/StockViewer/issues
Project-URL: Funding, https://trucomanx.github.io/en/funding.html
Project-URL: Documentation, https://github.com/trucomanx/StockViewer/tree/main/doc
Project-URL: Source, https://github.com/trucomanx/StockViewer
Keywords: writing,translate
Classifier: Programming Language :: Python :: 3
Classifier: Operating System :: OS Independent
Requires-Python: >=3.8
License-File: LICENSE
Requires-Dist: PyQt5
Requires-Dist: yfinance
Requires-Dist: pyqtgraph
Dynamic: license-file
